MANIFEST.in
README.md
setup.py
coolmit/__init__.py
coolmit/base.py
coolmit/cpu.py
coolmit.egg-info/PKG-INFO
coolmit.egg-info/SOURCES.txt
coolmit.egg-info/dependency_links.txt
coolmit.egg-info/entry_points.txt
coolmit.egg-info/pbr.json
coolmit.egg-info/requires.txt
coolmit.egg-info/top_level.txt