Metadata-Version: 2.1
Name: coolmit
Version: 0.2.0
Summary: Don't just commit; coolmit.
Home-page: https://github.com/awentzonline/coolmit
Author: Adam Wentz
Author-email: adam@adamwentz.com
License: MIT
Keywords: git cool commit
Classifier: Development Status :: 3 - Alpha
Classifier: Topic :: Utilities
Classifier: License :: OSI Approved :: MIT License
